Workbook

Sheet Cover
A1: Sweet Shop
A2: Requirements Traceability Matrix
A4: Document Version: | B4: 1.0
A5: Status: | B5: Draft for Review
A6: Date: | B6: April 2026
A7: Application URL: | B7: https://sweetshop.netlify.app
A8: Reference: | B8: Product Specification v2.0
A9: Derives from: | B9: Test Strategy v1.0 + Test Plan v1.0 + Test Cases v3.0
A11: Purpose
A12: This Requirements Traceability Matrix (RTM) provides bidirectional traceability between every documented requirement (FR-01 to FR-18 and NFR-01 to NFR-08) from the Product Specification v2.0 and the test cases that verify it. It is the single auditable artifact that proves no requirement is left untested and no test case is orphaned from a documented requirement.
A14: Sheets in this Workbook
A15: Sheet | B15: Description
A16: 1. Cover | B16: This sheet — purpose, version, sheet index
A17: 2. RTM (Forward) | B17: Requirement → Test Cases. The classic forward traceability view. Every FR/NFR mapped to its test cases with execution status.
A18: 3. RTM (Reverse) | B18: Test Case → Requirements. Reverse traceability — proves no orphan test cases.
A19: 4. Coverage Summary | B19: Counts and percentages: requirements covered, cases per priority, automation breakdown, status dashboard.
A20: 5. Test Case Master | B20: Full list of all 158 test cases with their attributes, used as the data source by the other sheets.
A21: 6. Defect Anchor | B21: Empty placeholder sheet for defect IDs raised against requirements during execution. Populated as defects are logged.
A22: 7. Execution Log | B22: Per-case execution status entry sheet — testers update Pass/Fail/Blocked here during the cycle.
A23: 8. Legend | B23: Definitions for priority, automation tag, status values.

Sheet RTM (Forward)
A1: Req ID | B1: Type | C1: Category | D1: Requirement | E1: Spec Reference | F1: Test Scenario | G1: Test Case IDs | H1: TC Count | I1: P0 | J1: P1 | K1: P2 | L1: P3 | M1: Executed | N1: Passed | O1: Failed | P1: Blocked | Q1: Coverage Status | R1: Defects (count)
A2: FR-01 | B2: Functional | C2: Product Browsing | D2: Users shall be able to view all 16 products on the Browse Sweets page | E2: Spec §11.1, §4.2 | F2: Browse Sweets — Catalogue Rendering | G2: TC-020, TC-021, TC-022, TC-023, TC-024, TC-025, TC-026 | H2: 7 | I2: 1 | K2: 2 | L2: 4 | M2: =SUMPRODUCT(ISNUMBER(MATCH('Execution Log'!A2:A159,{"TC-020","TC-021","TC-022","TC-023","TC-024","TC-025","TC-026"},0))*('Execution Log'!F2:F159<>"Not Run")) -> 0 | N2: =SUMPRODUCT(ISNUMBER(MATCH('Execution Log'!A2:A159,{"TC-020","TC-021","TC-022","TC-023","TC-024","TC-025","TC-026"},0))*('Execution Log'!F2:F159="Pass")) -> 0 | O2: =SUMPRODUCT(ISNUMBER(MATCH('Execution Log'!A2:A159,{"TC-020","TC-021","TC-022","TC-023","TC-024","TC-025","TC-026"},0))*('Execution Log'!F2:F159="Fail")) -> 0 | P2: =SUMPRODUCT(ISNUMBER(MATCH('Execution Log'!A2:A159,{"TC-020","TC-021","TC-022","TC-023","TC-024","TC-025","TC-026"},0))*('Execution Log'!F2:F159="Blocked")) -> 0 | Q2: Covered | R2: =SUMPRODUCT(ISNUMBER(MATCH('Execution Log'!A2:A159,{"TC-020","TC-021","TC-022","TC-023","TC-024","TC-025","TC-026"},0))*('Execution Log'!I2:I159<>"")) -> 0
A3: FR-02 | B3: Functional | C3: Product Browsing | D3: Each product shall display image, name, description, price, Add to Basket button | E3: Spec §11.1, §4.2 | F3: Product Card Structure | G3: TC-021, TC-022, TC-024, TC-025, TC-026 | H3: 5 | I3: 1 | K3: 1 | L3: 3 | M3: =SUMPRODUCT(ISNUMBER(MATCH('Execution Log'!A2:A159,{"TC-021","TC-022","TC-024","TC-025","TC-026"},0))*('Execution Log'!F2:F159<>"Not Run")) -> 0 | N3: =SUMPRODUCT(ISNUMBER(MATCH('Execution Log'!A2:A159,{"TC-021","TC-022","TC-024","TC-025","TC-026"},0))*('Execution Log'!F2:F159="Pass")) -> 0 | O3: =SUMPRODUCT(ISNUMBER(MATCH('Execution Log'!A2:A159,{"TC-021","TC-022","TC-024","TC-025","TC-026"},0))*('Execution Log'!F2:F159="Fail")) -> 0 | P3: =SUMPRODUCT(ISNUMBER(MATCH('Execution Log'!A2:A159,{"TC-021","TC-022","TC-024","TC-025","TC-026"},0))*('Execution Log'!F2:F159="Blocked")) -> 0 | Q3: Covered | R3: =SUMPRODUCT(ISNUMBER(MATCH('Execution Log'!A2:A159,{"TC-021","TC-022","TC-024","TC-025","TC-026"},0))*('Execution Log'!I2:I159<>"")) -> 0
A4: FR-03 | B4: Functional | C4: Product Browsing | D4: The homepage shall display a curated Most Popular section of 4 products | E4: Spec §11.1, §4.1 | F4: Home — Most Popular Section | G4: TC-010, TC-011, TC-012, TC-013 | H4: 4 | J4: 2 | K4: 1 | L4: 1 | M4: =SUMPRODUCT(ISNUMBER(MATCH('Execution Log'!A2:A159,{"TC-010","TC-011","TC-012","TC-013"},0))*('Execution Log'!F2:F159<>"Not Run")) -> 0 | N4: =SUMPRODUCT(ISNUMBER(MATCH('Execution Log'!A2:A159,{"TC-010","TC-011","TC-012","TC-013"},0))*('Execution Log'!F2:F159="Pass")) -> 0 | O4: =SUMPRODUCT(ISNUMBER(MATCH('Execution Log'!A2:A159,{"TC-010","TC-011","TC-012","TC-013"},0))*('Execution Log'!F2:F159="Fail")) -> 0 | P4: =SUMPRODUCT(ISNUMBER(MATCH('Execution Log'!A2:A159,{"TC-010","TC-011","TC-012","TC-013"},0))*('Execution Log'!F2:F159="Blocked")) -> 0 | Q4: Covered | R4: =SUMPRODUCT(ISNUMBER(MATCH('Execution Log'!A2:A159,{"TC-010","TC-011","TC-012","TC-013"},0))*('Execution Log'!I2:I159<>"")) -> 0
A5: FR-04 | B5: Functional | C5: Basket / Cart | D5: Users shall be able to add products from both Home and Browse Sweets pages | E5: Spec §11.2, §4.2.4 | F5: Add to Basket — Multi-source | G5: TC-030, TC-031, TC-033, TC-034, TC-035, TC-036, TC-037, TC-038 | H5: 8 | I5: 3 | J5: 1 | K5: 4 | M5: =SUMPRODUCT(ISNUMBER(MATCH('Execution Log'!A2:A159,{"TC-030","TC-031","TC-033","TC-034","TC-035","TC-036","TC-037","TC-038"},0))*('Execution Log'!F2:F159<>"Not Run")) -> 0 | N5: =SUMPRODUCT(ISNUMBER(MATCH('Execution Log'!A2:A159,{"TC-030","TC-031","TC-033","TC-034","TC-035","TC-036","TC-037","TC-038"},0))*('Execution Log'!F2:F159="Pass")) -> 0 | O5: =SUMPRODUCT(ISNUMBER(MATCH('Execution Log'!A2:A159,{"TC-030","TC-031","TC-033","TC-034","TC-035","TC-036","TC-037","TC-038"},0))*('Execution Log'!F2:F159="Fail")) -> 0 | P5: =SUMPRODUCT(ISNUMBER(MATCH('Execution Log'!A2:A159,{"TC-030","TC-031","TC-033","TC-034","TC-035","TC-036","TC-037","TC-038"},0))*('Execution Log'!F2:F159="Blocked")) -> 0 | Q5: Covered | R5: =SUMPRODUCT(ISNUMBER(MATCH('Execution Log'!A2:A159,{"TC-030","TC-031","TC-033","TC-034","TC-035","TC-036","TC-037","TC-038"},0))*('Execution Log'!I2:I159<>"")) -> 0
A6: FR-05 | B6: Functional | C6: Basket / Cart | D6: The basket item count in the navbar shall update in real-time | E6: Spec §11.2, §3.1 | F6: Navbar Basket Counter | G6: TC-007, TC-008, TC-030, TC-031, TC-032, TC-034, TC-050, TC-217 | H6: 8 | I6: 5 | J6: 1 | L6: 2 | M6: =SUMPRODUCT(ISNUMBER(MATCH('Execution Log'!A2:A159,{"TC-007","TC-008","TC-030","TC-031","TC-032","TC-034","TC-050","TC-217"},0))*('Execution Log'!F2:F159<>"Not Run")) -> 0 | N6: =SUMPRODUCT(ISNUMBER(MATCH('Execution Log'!A2:A159,{"TC-007","TC-008","TC-030","TC-031","TC-032","TC-034","TC-050","TC-217"},0))*('Execution Log'!F2:F159="Pass")) -> 0 | O6: =SUMPRODUCT(ISNUMBER(MATCH('Execution Log'!A2:A159,{"TC-007","TC-008","TC-030","TC-031","TC-032","TC-034","TC-050","TC-217"},0))*('Execution Log'!F2:F159="Fail")) -> 0 | P6: =SUMPRODUCT(ISNUMBER(MATCH('Execution Log'!A2:A159,{"TC-007","TC-008","TC-030","TC-031","TC-032","TC-034","TC-050","TC-217"},0))*('Execution Log'!F2:F159="Blocked")) -> 0 | Q6: Covered | R6: =SUMPRODUCT(ISNUMBER(MATCH('Execution Log'!A2:A159,{"TC-007","TC-008","TC-030","TC-031","TC-032","TC-034","TC-050","TC-217"},0))*('Execution Log'!I2:I159<>"")) -> 0
A7: FR-06 | B7: Functional | C7: Basket / Cart | D7: Users shall be able to empty the basket via Empty Basket control | E7: Spec §11.2, §4.3.4 | F7: Empty Basket Flow | G7: TC-050, TC-051, TC-078, TC-094, TC-169 | H7: 5 | J7: 1 | K7: 1 | L7: 3 | M7: =SUMPRODUCT(ISNUMBER(MATCH('Execution Log'!A2:A159,{"TC-050","TC-051","TC-078","TC-094","TC-169"},0))*('Execution Log'!F2:F159<>"Not Run")) -> 0 | N7: =SUMPRODUCT(ISNUMBER(MATCH('Execution Log'!A2:A159,{"TC-050","TC-051","TC-078","TC-094","TC-169"},0))*('Execution Log'!F2:F159="Pass")) -> 0 | O7: =SUMPRODUCT(ISNUMBER(MATCH('Execution Log'!A2:A159,{"TC-050","TC-051","TC-078","TC-094","TC-169"},0))*('Execution Log'!F2:F159="Fail")) -> 0 | P7: =SUMPRODUCT(ISNUMBER(MATCH('Execution Log'!A2:A159,{"TC-050","TC-051","TC-078","TC-094","TC-169"},0))*('Execution Log'!F2:F159="Blocked")) -> 0 | Q7: Covered | R7: =SUMPRODUCT(ISNUMBER(MATCH('Execution Log'!A2:A159,{"TC-050","TC-051","TC-078","TC-094","TC-169"},0))*('Execution Log'!I2:I159<>"")) -> 0
A8: FR-07 | B8: Functional | C8: Basket / Cart | D8: Users shall be able to select a delivery method (Collect or Standard Shipping) | E8: Spec §11.2, §4.3.3 | F8: Delivery Selection | G8: TC-060, TC-061, TC-062, TC-063, TC-064, TC-091 | H8: 6 | I8: 1 | J8: 2 | K8: 3 | M8: =SUMPRODUCT(ISNUMBER(MATCH('Execution Log'!A2:A159,{"TC-060","TC-061","TC-062","TC-063","TC-064","TC-091"},0))*('Execution Log'!F2:F159<>"Not Run")) -> 0 | N8: =SUMPRODUCT(ISNUMBER(MATCH('Execution Log'!A2:A159,{"TC-060","TC-061","TC-062","TC-063","TC-064","TC-091"},0))*('Execution Log'!F2:F159="Pass")) -> 0 | O8: =SUMPRODUCT(ISNUMBER(MATCH('Execution Log'!A2:A159,{"TC-060","TC-061","TC-062","TC-063","TC-064","TC-091"},0))*('Execution Log'!F2:F159="Fail")) -> 0 | P8: =SUMPRODUCT(ISNUMBER(MATCH('Execution Log'!A2:A159,{"TC-060","TC-061","TC-062","TC-063","TC-064","TC-091"},0))*('Execution Log'!F2:F159="Blocked")) -> 0 | Q8: Covered | R8: =SUMPRODUCT(ISNUMBER(MATCH('Execution Log'!A2:A159,{"TC-060","TC-061","TC-062","TC-063","TC-064","TC-091"},0))*('Execution Log'!I2:I159<>"")) -> 0
A9: FR-08 | B9: Functional | C9: Basket / Cart | D9: Users shall be able to enter and attempt to redeem a promotional code | E9: Spec §11.2, §4.3.4 | F9: Promo Code Redemption | G9: TC-070, TC-071, TC-072, TC-073, TC-074, TC-075, TC-076, TC-077, TC-078, TC-079 | H9: 10 | J9: 2 | K9: 3 | L9: 5 | M9: =SUMPRODUCT(ISNUMBER(MATCH('Execution Log'!A2:A159,{"TC-070","TC-071","TC-072","TC-073","TC-074","TC-075","TC-076","TC-077","TC-078","TC-079"},0))*('Execution Log'!F2:F159<>"Not Run")) -> 0 | N9: =SUMPRODUCT(ISNUMBER(MATCH('Execution Log'!A2:A159,{"TC-070","TC-071","TC-072","TC-073","TC-074","TC-075","TC-076","TC-077","TC-078","TC-079"},0))*('Execution Log'!F2:F159="Pass")) -> 0 | O9: =SUMPRODUCT(ISNUMBER(MATCH('Execution Log'!A2:A159,{"TC-070","TC-071","TC-072","TC-073","TC-074","TC-075","TC-076","TC-077","TC-078","TC-079"},0))*('Execution Log'!F2:F159="Fail")) -> 0 | P9: =SUMPRODUCT(ISNUMBER(MATCH('Execution Log'!A2:A159,{"TC-070","TC-071","TC-072","TC-073","TC-074","TC-075","TC-076","TC-077","TC-078","TC-079"},0))*('Execution Log'!F2:F159="Blocked")) -> 0 | Q9: Covered | R9: =SUMPRODUCT(ISNUMBER(MATCH('Execution Log'!A2:A159,{"TC-070","TC-071","TC-072","TC-073","TC-074","TC-075","TC-076","TC-077","TC-078","TC-079"},0))*('Execution Log'!I2:I159<>"")) -> 0
A10: FR-09 | B10: Functional | C10: Basket / Cart | D10: The basket shall display the current item list and count dynamically | E10: Spec §11.2, §4.3.2 | F10: Basket Display & Subtotal | G10: TC-041, TC-042, TC-043, TC-044, TC-045, TC-080, TC-081, TC-082, TC-083, TC-084, TC-086, TC-087, TC-088, TC-091, TC-092, TC-093, TC-094, TC-095, TC-096 | H10: 19 | I10: 8 | J10: 4 | K10: 6 | L10: 1 | M10: =SUMPRODUCT(ISNUMBER(MATCH('Execution Log'!A2:A159,{"TC-041","TC-042","TC-043","TC-044","TC-045","TC-080","TC-081","TC-082","TC-083","TC-084","TC-086","TC-087","TC-088","TC-091","TC-092","TC-093","TC-094","TC-095","TC-096"},0))*('Execution Log'!F2:F159<>"Not Run")) -> 0 | N10: =SUMPRODUCT(ISNUMBER(MATCH('Execution Log'!A2:A159,{"TC-041","TC-042","TC-043","TC-044","TC-045","TC-080","TC-081","TC-082","TC-083","TC-084","TC-086","TC-087","TC-088","TC-091","TC-092","TC-093","TC-094","TC-095","TC-096"},0))*('Execution Log'!F2:F159="Pass")) -> 0 | O10: =SUMPRODUCT(ISNUMBER(MATCH('Execution Log'!A2:A159,{"TC-041","TC-042","TC-043","TC-044","TC-045","TC-080","TC-081","TC-082","TC-083","TC-084","TC-086","TC-087","TC-088","TC-091","TC-092","TC-093","TC-094","TC-095","TC-096"},0))*('Execution Log'!F2:F159="Fail")) -> 0 | P10: =SUMPRODUCT(ISNUMBER(MATCH('Execution Log'!A2:A159,{"TC-041","TC-042","TC-043","TC-044","TC-045","TC-080","TC-081","TC-082","TC-083","TC-084","TC-086","TC-087","TC-088","TC-091","TC-092","TC-093","TC-094","TC-095","TC-096"},0))*('Execution Log'!F2:F159="Blocked")) -> 0 | Q10: Covered | R10: =SUMPRODUCT(ISNUMBER(MATCH('Execution Log'!A2:A159,{"TC-041","TC-042","TC-043","TC-044","TC-045","TC-080","TC-081","TC-082","TC-083","TC-084","TC-086","TC-087","TC-088","TC-091","TC-092","TC-093","TC-094","TC-095","TC-096"},0))*('Execution Log'!I2:I159<>"")) -> 0
A11: FR-10 | B11: Functional | C11: Basket / Cart | D11: The order total shall update dynamically when delivery option changes | E11: Spec §11.2, §5.7 | F11: Order Total Recalculation | G11: TC-043, TC-061, TC-062, TC-079, TC-080, TC-081, TC-083, TC-085, TC-089, TC-090, TC-095, TC-096 | H11: 12 | I11: 5 | J11: 5 | K11: 2 | M11: =SUMPRODUCT(ISNUMBER(MATCH('Execution Log'!A2:A159,{"TC-043","TC-061","TC-062","TC-079","TC-080","TC-081","TC-083","TC-085","TC-089","TC-090","TC-095","TC-096"},0))*('Execution Log'!F2:F159<>"Not Run")) -> 0 | N11: =SUMPRODUCT(ISNUMBER(MATCH('Execution Log'!A2:A159,{"TC-043","TC-061","TC-062","TC-079","TC-080","TC-081","TC-083","TC-085","TC-089","TC-090","TC-095","TC-096"},0))*('Execution Log'!F2:F159="Pass")) -> 0 | O11: =SUMPRODUCT(ISNUMBER(MATCH('Execution Log'!A2:A159,{"TC-043","TC-061","TC-062","TC-079","TC-080","TC-081","TC-083","TC-085","TC-089","TC-090","TC-095","TC-096"},0))*('Execution Log'!F2:F159="Fail")) -> 0 | P11: =SUMPRODUCT(ISNUMBER(MATCH('Execution Log'!A2:A159,{"TC-043","TC-061","TC-062","TC-079","TC-080","TC-081","TC-083","TC-085","TC-089","TC-090","TC-095","TC-096"},0))*('Execution Log'!F2:F159="Blocked")) -> 0 | Q11: Covered | R11: =SUMPRODUCT(ISNUMBER(MATCH('Execution Log'!A2:A159,{"TC-043","TC-061","TC-062","TC-079","TC-080","TC-081","TC-083","TC-085","TC-089","TC-090","TC-095","TC-096"},0))*('Execution Log'!I2:I159<>"")) -> 0
A12: FR-11 | B12: Functional | C12: Checkout | D12: Users shall fill in a billing address form with field-level validation | E12: Spec §11.3, §4.3.5 | F12: Billing Form Validation | G12: TC-110, TC-111, TC-112, TC-113, TC-114, TC-115, TC-116, TC-117, TC-118, TC-119, TC-120, TC-121, TC-122, TC-123 | H12: 14 | I12: 1 | J12: 8 | K12: 5 | M12: =SUMPRODUCT(ISNUMBER(MATCH('Execution Log'!A2:A159,{"TC-110","TC-111","TC-112","TC-113","TC-114","TC-115","TC-116","TC-117","TC-118","TC-119","TC-120","TC-121","TC-122","TC-123"},0))*('Execution Log'!F2:F159<>"Not Run")) -> 0 | N12: =SUMPRODUCT(ISNUMBER(MATCH('Execution Log'!A2:A159,{"TC-110","TC-111","TC-112","TC-113","TC-114","TC-115","TC-116","TC-117","TC-118","TC-119","TC-120","TC-121","TC-122","TC-123"},0))*('Execution Log'!F2:F159="Pass")) -> 0 | O12: =SUMPRODUCT(ISNUMBER(MATCH('Execution Log'!A2:A159,{"TC-110","TC-111","TC-112","TC-113","TC-114","TC-115","TC-116","TC-117","TC-118","TC-119","TC-120","TC-121","TC-122","TC-123"},0))*('Execution Log'!F2:F159="Fail")) -> 0 | P12: =SUMPRODUCT(ISNUMBER(MATCH('Execution Log'!A2:A159,{"TC-110","TC-111","TC-112","TC-113","TC-114","TC-115","TC-116","TC-117","TC-118","TC-119","TC-120","TC-121","TC-122","TC-123"},0))*('Execution Log'!F2:F159="Blocked")) -> 0 | Q12: Covered | R12: =SUMPRODUCT(ISNUMBER(MATCH('Execution Log'!A2:A159,{"TC-110","TC-111","TC-112","TC-113","TC-114","TC-115","TC-116","TC-117","TC-118","TC-119","TC-120","TC-121","TC-122","TC-123"},0))*('Execution Log'!I2:I159<>"")) -> 0
A13: FR-12 | B13: Functional | C13: Checkout | D13: Users shall fill in a payment details form with field-level validation | E13: Spec §11.3, §4.3.6 | F13: Payment Form Validation | G13: TC-130, TC-131, TC-132, TC-133, TC-134, TC-135, TC-136, TC-137, TC-138 | H13: 9 | J13: 5 | K13: 3 | L13: 1 | M13: =SUMPRODUCT(ISNUMBER(MATCH('Execution Log'!A2:A159,{"TC-130","TC-131","TC-132","TC-133","TC-134","TC-135","TC-136","TC-137","TC-138"},0))*('Execution Log'!F2:F159<>"Not Run")) -> 0 | N13: =SUMPRODUCT(ISNUMBER(MATCH('Execution Log'!A2:A159,{"TC-130","TC-131","TC-132","TC-133","TC-134","TC-135","TC-136","TC-137","TC-138"},0))*('Execution Log'!F2:F159="Pass")) -> 0 | O13: =SUMPRODUCT(ISNUMBER(MATCH('Execution Log'!A2:A159,{"TC-130","TC-131","TC-132","TC-133","TC-134","TC-135","TC-136","TC-137","TC-138"},0))*('Execution Log'!F2:F159="Fail")) -> 0 | P13: =SUMPRODUCT(ISNUMBER(MATCH('Execution Log'!A2:A159,{"TC-130","TC-131","TC-132","TC-133","TC-134","TC-135","TC-136","TC-137","TC-138"},0))*('Execution Log'!F2:F159="Blocked")) -> 0 | Q13: Covered | R13: =SUMPRODUCT(ISNUMBER(MATCH('Execution Log'!A2:A159,{"TC-130","TC-131","TC-132","TC-133","TC-134","TC-135","TC-136","TC-137","TC-138"},0))*('Execution Log'!I2:I159<>"")) -> 0
A14: FR-13 | B14: Functional | C14: Checkout | D14: Continue to checkout shall trigger full form validation | E14: Spec §11.3, §4.3.7 | F14: Checkout Submission | G14: TC-111, TC-140, TC-141, TC-142, TC-143, TC-144, TC-145, TC-146 | H14: 8 | I14: 2 | J14: 1 | K14: 5 | M14: =SUMPRODUCT(ISNUMBER(MATCH('Execution Log'!A2:A159,{"TC-111","TC-140","TC-141","TC-142","TC-143","TC-144","TC-145","TC-146"},0))*('Execution Log'!F2:F159<>"Not Run")) -> 0 | N14: =SUMPRODUCT(ISNUMBER(MATCH('Execution Log'!A2:A159,{"TC-111","TC-140","TC-141","TC-142","TC-143","TC-144","TC-145","TC-146"},0))*('Execution Log'!F2:F159="Pass")) -> 0 | O14: =SUMPRODUCT(ISNUMBER(MATCH('Execution Log'!A2:A159,{"TC-111","TC-140","TC-141","TC-142","TC-143","TC-144","TC-145","TC-146"},0))*('Execution Log'!F2:F159="Fail")) -> 0 | P14: =SUMPRODUCT(ISNUMBER(MATCH('Execution Log'!A2:A159,{"TC-111","TC-140","TC-141","TC-142","TC-143","TC-144","TC-145","TC-146"},0))*('Execution Log'!F2:F159="Blocked")) -> 0 | Q14: Covered | R14: =SUMPRODUCT(ISNUMBER(MATCH('Execution Log'!A2:A159,{"TC-111","TC-140","TC-141","TC-142","TC-143","TC-144","TC-145","TC-146"},0))*('Execution Log'!I2:I159<>"")) -> 0
A15: FR-14 | B15: Functional | C15: Authentication | D15: Users shall be able to attempt login with email and password | E15: Spec §11.4, §4.4 | F15: Login Form & Validation | G15: TC-100, TC-101, TC-102, TC-103, TC-104, TC-106, TC-107, TC-108 | H15: 8 | J15: 3 | K15: 3 | L15: 2 | M15: =SUMPRODUCT(ISNUMBER(MATCH('Execution Log'!A2:A159,{"TC-100","TC-101","TC-102","TC-103","TC-104","TC-106","TC-107","TC-108"},0))*('Execution Log'!F2:F159<>"Not Run")) -> 0 | N15: =SUMPRODUCT(ISNUMBER(MATCH('Execution Log'!A2:A159,{"TC-100","TC-101","TC-102","TC-103","TC-104","TC-106","TC-107","TC-108"},0))*('Execution Log'!F2:F159="Pass")) -> 0 | O15: =SUMPRODUCT(ISNUMBER(MATCH('Execution Log'!A2:A159,{"TC-100","TC-101","TC-102","TC-103","TC-104","TC-106","TC-107","TC-108"},0))*('Execution Log'!F2:F159="Fail")) -> 0 | P15: =SUMPRODUCT(ISNUMBER(MATCH('Execution Log'!A2:A159,{"TC-100","TC-101","TC-102","TC-103","TC-104","TC-106","TC-107","TC-108"},0))*('Execution Log'!F2:F159="Blocked")) -> 0 | Q15: Covered | R15: =SUMPRODUCT(ISNUMBER(MATCH('Execution Log'!A2:A159,{"TC-100","TC-101","TC-102","TC-103","TC-104","TC-106","TC-107","TC-108"},0))*('Execution Log'!I2:I159<>"")) -> 0
A16: FR-15 | B16: Functional | C16: Authentication | D16: Social login link icons shall be displayed on the Login page | E16: Spec §11.4, §4.4.3 | F16: Social Login Display | G16: TC-230 | H16: 1 | L16: 1 | M16: =SUMPRODUCT(ISNUMBER(MATCH('Execution Log'!A2:A159,{"TC-230"},0))*('Execution Log'!F2:F159<>"Not Run")) -> 0 | N16: =SUMPRODUCT(ISNUMBER(MATCH('Execution Log'!A2:A159,{"TC-230"},0))*('Execution Log'!F2:F159="Pass")) -> 0 | O16: =SUMPRODUCT(ISNUMBER(MATCH('Execution Log'!A2:A159,{"TC-230"},0))*('Execution Log'!F2:F159="Fail")) -> 0 | P16: =SUMPRODUCT(ISNUMBER(MATCH('Execution Log'!A2:A159,{"TC-230"},0))*('Execution Log'!F2:F159="Blocked")) -> 0 | Q16: Covered | R16: =SUMPRODUCT(ISNUMBER(MATCH('Execution Log'!A2:A159,{"TC-230"},0))*('Execution Log'!I2:I159<>"")) -> 0
A17: FR-16 | B17: Functional | C17: Navigation | D17: A persistent navigation bar shall be present on all pages | E17: Spec §11.5, §3.1 | F17: Persistent Navbar | G17: TC-001, TC-002, TC-005, TC-008, TC-009, TC-245 | H17: 6 | I17: 2 | L17: 4 | M17: =SUMPRODUCT(ISNUMBER(MATCH('Execution Log'!A2:A159,{"TC-001","TC-002","TC-005","TC-008","TC-009","TC-245"},0))*('Execution Log'!F2:F159<>"Not Run")) -> 0 | N17: =SUMPRODUCT(ISNUMBER(MATCH('Execution Log'!A2:A159,{"TC-001","TC-002","TC-005","TC-008","TC-009","TC-245"},0))*('Execution Log'!F2:F159="Pass")) -> 0 | O17: =SUMPRODUCT(ISNUMBER(MATCH('Execution Log'!A2:A159,{"TC-001","TC-002","TC-005","TC-008","TC-009","TC-245"},0))*('Execution Log'!F2:F159="Fail")) -> 0 | P17: =SUMPRODUCT(ISNUMBER(MATCH('Execution Log'!A2:A159,{"TC-001","TC-002","TC-005","TC-008","TC-009","TC-245"},0))*('Execution Log'!F2:F159="Blocked")) -> 0 | Q17: Covered | R17: =SUMPRODUCT(ISNUMBER(MATCH('Execution Log'!A2:A159,{"TC-001","TC-002","TC-005","TC-008","TC-009","TC-245"},0))*('Execution Log'!I2:I159<>"")) -> 0
A18: FR-17 | B18: Functional | C18: Navigation | D18: The active page shall be visually indicated in the navbar | E18: Spec §11.5, §3.1 | F18: Active Page Indicator | G18: TC-003 | H18: 1 | K18: 1 | M18: =SUMPRODUCT(ISNUMBER(MATCH('Execution Log'!A2:A159,{"TC-003"},0))*('Execution Log'!F2:F159<>"Not Run")) -> 0 | N18: =SUMPRODUCT(ISNUMBER(MATCH('Execution Log'!A2:A159,{"TC-003"},0))*('Execution Log'!F2:F159="Pass")) -> 0 | O18: =SUMPRODUCT(ISNUMBER(MATCH('Execution Log'!A2:A159,{"TC-003"},0))*('Execution Log'!F2:F159="Fail")) -> 0 | P18: =SUMPRODUCT(ISNUMBER(MATCH('Execution Log'!A2:A159,{"TC-003"},0))*('Execution Log'!F2:F159="Blocked")) -> 0 | Q18: Covered | R18: =SUMPRODUCT(ISNUMBER(MATCH('Execution Log'!A2:A159,{"TC-003"},0))*('Execution Log'!I2:I159<>"")) -> 0
A19: FR-18 | B19: Functional | C19: Navigation | D19: The logo shall link back to the homepage from all pages | E19: Spec §11.5, §3.1 | F19: Logo Home Link | G19: TC-002, TC-004 | H19: 2 | I19: 1 | K19: 1 | M19: =SUMPRODUCT(ISNUMBER(MATCH('Execution Log'!A2:A159,{"TC-002","TC-004"},0))*('Execution Log'!F2:F159<>"Not Run")) -> 0 | N19: =SUMPRODUCT(ISNUMBER(MATCH('Execution Log'!A2:A159,{"TC-002","TC-004"},0))*('Execution Log'!F2:F159="Pass")) -> 0 | O19: =SUMPRODUCT(ISNUMBER(MATCH('Execution Log'!A2:A159,{"TC-002","TC-004"},0))*('Execution Log'!F2:F159="Fail")) -> 0 | P19: =SUMPRODUCT(ISNUMBER(MATCH('Execution Log'!A2:A159,{"TC-002","TC-004"},0))*('Execution Log'!F2:F159="Blocked")) -> 0 | Q19: Covered | R19: =SUMPRODUCT(ISNUMBER(MATCH('Execution Log'!A2:A159,{"TC-002","TC-004"},0))*('Execution Log'!I2:I159<>"")) -> 0
A20: NFR-01 | B20: Non-Functional | C20: Usability | D20: All forms shall display inline validation error messages | E20: Spec §12.1 | F20: Inline Error Messages | G20: TC-070, TC-101, TC-111, TC-140, TC-143 | H20: 5 | I20: 2 | J20: 2 | K20: 1 | M20: =SUMPRODUCT(ISNUMBER(MATCH('Execution Log'!A2:A159,{"TC-070","TC-101","TC-111","TC-140","TC-143"},0))*('Execution Log'!F2:F159<>"Not Run")) -> 0 | N20: =SUMPRODUCT(ISNUMBER(MATCH('Execution Log'!A2:A159,{"TC-070","TC-101","TC-111","TC-140","TC-143"},0))*('Execution Log'!F2:F159="Pass")) -> 0 | O20: =SUMPRODUCT(ISNUMBER(MATCH('Execution Log'!A2:A159,{"TC-070","TC-101","TC-111","TC-140","TC-143"},0))*('Execution Log'!F2:F159="Fail")) -> 0 | P20: =SUMPRODUCT(ISNUMBER(MATCH('Execution Log'!A2:A159,{"TC-070","TC-101","TC-111","TC-140","TC-143"},0))*('Execution Log'!F2:F159="Blocked")) -> 0 | Q20: Covered | R20: =SUMPRODUCT(ISNUMBER(MATCH('Execution Log'!A2:A159,{"TC-070","TC-101","TC-111","TC-140","TC-143"},0))*('Execution Log'!I2:I159<>"")) -> 0
A21: NFR-02 | B21: Non-Functional | C21: Usability | D21: The application shall be fully navigable without requiring login | E21: Spec §12.1, §14.5 | F21: Open Navigation (No Auth) | G21: TC-001, TC-170, TC-206 | H21: 3 | I21: 1 | K21: 1 | L21: 1 | M21: =SUMPRODUCT(ISNUMBER(MATCH('Execution Log'!A2:A159,{"TC-001","TC-170","TC-206"},0))*('Execution Log'!F2:F159<>"Not Run")) -> 0 | N21: =SUMPRODUCT(ISNUMBER(MATCH('Execution Log'!A2:A159,{"TC-001","TC-170","TC-206"},0))*('Execution Log'!F2:F159="Pass")) -> 0 | O21: =SUMPRODUCT(ISNUMBER(MATCH('Execution Log'!A2:A159,{"TC-001","TC-170","TC-206"},0))*('Execution Log'!F2:F159="Fail")) -> 0 | P21: =SUMPRODUCT(ISNUMBER(MATCH('Execution Log'!A2:A159,{"TC-001","TC-170","TC-206"},0))*('Execution Log'!F2:F159="Blocked")) -> 0 | Q21: Covered | R21: =SUMPRODUCT(ISNUMBER(MATCH('Execution Log'!A2:A159,{"TC-001","TC-170","TC-206"},0))*('Execution Log'!I2:I159<>"")) -> 0
A22: NFR-03 | B22: Non-Functional | C22: Usability | D22: Validation messages shall be displayed adjacent to the field that triggered them | E22: Spec §12.1, §5.3 | F22: Error-Field Adjacency | G22: TC-143 | H22: 1 | K22: 1 | M22: =SUMPRODUCT(ISNUMBER(MATCH('Execution Log'!A2:A159,{"TC-143"},0))*('Execution Log'!F2:F159<>"Not Run")) -> 0 | N22: =SUMPRODUCT(ISNUMBER(MATCH('Execution Log'!A2:A159,{"TC-143"},0))*('Execution Log'!F2:F159="Pass")) -> 0 | O22: =SUMPRODUCT(ISNUMBER(MATCH('Execution Log'!A2:A159,{"TC-143"},0))*('Execution Log'!F2:F159="Fail")) -> 0 | P22: =SUMPRODUCT(ISNUMBER(MATCH('Execution Log'!A2:A159,{"TC-143"},0))*('Execution Log'!F2:F159="Blocked")) -> 0 | Q22: Covered | R22: =SUMPRODUCT(ISNUMBER(MATCH('Execution Log'!A2:A159,{"TC-143"},0))*('Execution Log'!I2:I159<>"")) -> 0
A23: NFR-04 | B23: Non-Functional | C23: Compatibility | D23: The application is primarily designed for Google Chrome | E23: Spec §12.2 | F23: Chrome Compatibility | G23: TC-180, TC-181, TC-240, TC-241 | H23: 4 | J23: 2 | L23: 2 | M23: =SUMPRODUCT(ISNUMBER(MATCH('Execution Log'!A2:A159,{"TC-180","TC-181","TC-240","TC-241"},0))*('Execution Log'!F2:F159<>"Not Run")) -> 0 | N23: =SUMPRODUCT(ISNUMBER(MATCH('Execution Log'!A2:A159,{"TC-180","TC-181","TC-240","TC-241"},0))*('Execution Log'!F2:F159="Pass")) -> 0 | O23: =SUMPRODUCT(ISNUMBER(MATCH('Execution Log'!A2:A159,{"TC-180","TC-181","TC-240","TC-241"},0))*('Execution Log'!F2:F159="Fail")) -> 0 | P23: =SUMPRODUCT(ISNUMBER(MATCH('Execution Log'!A2:A159,{"TC-180","TC-181","TC-240","TC-241"},0))*('Execution Log'!F2:F159="Blocked")) -> 0 | Q23: Covered | R23: =SUMPRODUCT(ISNUMBER(MATCH('Execution Log'!A2:A159,{"TC-180","TC-181","TC-240","TC-241"},0))*('Execution Log'!I2:I159<>"")) -> 0
A24: NFR-05 | B24: Non-Functional | C24: Compatibility | D24: Basic functionality verified in Firefox and Safari | E24: Spec §12.2 | F24: Firefox + Safari Compatibility | G24: TC-180, TC-181 | H24: 2 | J24: 2 | M24: =SUMPRODUCT(ISNUMBER(MATCH('Execution Log'!A2:A159,{"TC-180","TC-181"},0))*('Execution Log'!F2:F159<>"Not Run")) -> 0 | N24: =SUMPRODUCT(ISNUMBER(MATCH('Execution Log'!A2:A159,{"TC-180","TC-181"},0))*('Execution Log'!F2:F159="Pass")) -> 0 | O24: =SUMPRODUCT(ISNUMBER(MATCH('Execution Log'!A2:A159,{"TC-180","TC-181"},0))*('Execution Log'!F2:F159="Fail")) -> 0 | P24: =SUMPRODUCT(ISNUMBER(MATCH('Execution Log'!A2:A159,{"TC-180","TC-181"},0))*('Execution Log'!F2:F159="Blocked")) -> 0 | Q24: Covered | R24: =SUMPRODUCT(ISNUMBER(MATCH('Execution Log'!A2:A159,{"TC-180","TC-181"},0))*('Execution Log'!I2:I159<>"")) -> 0
A25: NFR-06 | B25: Non-Functional | C25: Accessibility | D25: Product images shall include descriptive alt text | E25: Spec §12.3 | F25: Image Alt Text | G25: TC-210, TC-213, TC-215 | H25: 3 | K25: 2 | L25: 1 | M25: =SUMPRODUCT(ISNUMBER(MATCH('Execution Log'!A2:A159,{"TC-210","TC-213","TC-215"},0))*('Execution Log'!F2:F159<>"Not Run")) -> 0 | N25: =SUMPRODUCT(ISNUMBER(MATCH('Execution Log'!A2:A159,{"TC-210","TC-213","TC-215"},0))*('Execution Log'!F2:F159="Pass")) -> 0 | O25: =SUMPRODUCT(ISNUMBER(MATCH('Execution Log'!A2:A159,{"TC-210","TC-213","TC-215"},0))*('Execution Log'!F2:F159="Fail")) -> 0 | P25: =SUMPRODUCT(ISNUMBER(MATCH('Execution Log'!A2:A159,{"TC-210","TC-213","TC-215"},0))*('Execution Log'!F2:F159="Blocked")) -> 0 | Q25: Covered | R25: =SUMPRODUCT(ISNUMBER(MATCH('Execution Log'!A2:A159,{"TC-210","TC-213","TC-215"},0))*('Execution Log'!I2:I159<>"")) -> 0
A26: NFR-07 | B26: Non-Functional | C26: Accessibility | D26: Form inputs shall be associated with visible labels | E26: Spec §12.3 | F26: Form Label Association | G26: TC-121, TC-122, TC-145, TC-211, TC-213, TC-214, TC-216 | H26: 7 | K26: 5 | L26: 2 | M26: =SUMPRODUCT(ISNUMBER(MATCH('Execution Log'!A2:A159,{"TC-121","TC-122","TC-145","TC-211","TC-213","TC-214","TC-216"},0))*('Execution Log'!F2:F159<>"Not Run")) -> 0 | N26: =SUMPRODUCT(ISNUMBER(MATCH('Execution Log'!A2:A159,{"TC-121","TC-122","TC-145","TC-211","TC-213","TC-214","TC-216"},0))*('Execution Log'!F2:F159="Pass")) -> 0 | O26: =SUMPRODUCT(ISNUMBER(MATCH('Execution Log'!A2:A159,{"TC-121","TC-122","TC-145","TC-211","TC-213","TC-214","TC-216"},0))*('Execution Log'!F2:F159="Fail")) -> 0 | P26: =SUMPRODUCT(ISNUMBER(MATCH('Execution Log'!A2:A159,{"TC-121","TC-122","TC-145","TC-211","TC-213","TC-214","TC-216"},0))*('Execution Log'!F2:F159="Blocked")) -> 0 | Q26: Covered | R26: =SUMPRODUCT(ISNUMBER(MATCH('Execution Log'!A2:A159,{"TC-121","TC-122","TC-145","TC-211","TC-213","TC-214","TC-216"},0))*('Execution Log'!I2:I159<>"")) -> 0
A27: NFR-08 | B27: Non-Functional | C27: Accessibility | D27: Error messages shall be programmatically associated with their fields | E27: Spec §12.3 | F27: Error-Field A11y Association | G27: TC-212, TC-213, TC-217 | H27: 3 | K27: 2 | L27: 1 | M27: =SUMPRODUCT(ISNUMBER(MATCH('Execution Log'!A2:A159,{"TC-212","TC-213","TC-217"},0))*('Execution Log'!F2:F159<>"Not Run")) -> 0 | N27: =SUMPRODUCT(ISNUMBER(MATCH('Execution Log'!A2:A159,{"TC-212","TC-213","TC-217"},0))*('Execution Log'!F2:F159="Pass")) -> 0 | O27: =SUMPRODUCT(ISNUMBER(MATCH('Execution Log'!A2:A159,{"TC-212","TC-213","TC-217"},0))*('Execution Log'!F2:F159="Fail")) -> 0 | P27: =SUMPRODUCT(ISNUMBER(MATCH('Execution Log'!A2:A159,{"TC-212","TC-213","TC-217"},0))*('Execution Log'!F2:F159="Blocked")) -> 0 | Q27: Covered | R27: =SUMPRODUCT(ISNUMBER(MATCH('Execution Log'!A2:A159,{"TC-212","TC-213","TC-217"},0))*('Execution Log'!I2:I159<>"")) -> 0
A28: TOTAL | H28: =SUM(H2:H27) -> 161 | I28: =SUM(I2:I27) -> 33 | J28: =SUM(J2:J27) -> 41 | K28: =SUM(K2:K27) -> 53 | L28: =SUM(L2:L27) -> 34 | M28: =SUM(M2:M27) -> 0 | N28: =SUM(N2:N27) -> 0 | O28: =SUM(O2:O27) -> 0 | P28: =SUM(P2:P27) -> 0 | Q28: =COUNTIF(Q2:Q27,"Covered")&" of "&26 -> 26 of 26

Sheet Test Case Master
A1: TC ID | B1: Module | C1: Title | D1: Priority | E1: Type | F1: Automation | G1: Requirements | H1: Defect Hint If Fails
A2: TC-001 | B2: Navigation | C2: Verify all 5 pages load successfully via direct URL | D2: P0 | E2: Smoke | F2: Smoke | G2: FR-16 | H2: Page-load failure / routing bug / broken build
A3: TC-002 | B3: Navigation | C3: Verify navbar links navigate to correct pages | D3: P0 | E3: Functional | F3: Smoke | G3: FR-16, FR-18 | H3: Routing / navbar link bug
A4: TC-003 | B4: Navigation | C4: Verify navbar active-state highlight reflects current page | D4: P2 | E4: UI | F4: Regression | G4: FR-17 | H4: CSS / active-state bug
A5: TC-004 | B5: Navigation | C5: Verify logo from any page returns user to home | D5: P2 | E5: Functional | F5: Regression | G5: FR-18 | H5: Logo link broken / wrong href
A6: TC-005 | B6: Navigation | C6: Verify footer is present on all pages with correct copyright | D6: P3 | E6: UI | F6: Regression | G6: — | H6: Footer template missing / wrong text
A7: TC-006 | B7: Navigation | C7: Verify intentional broken /bout link is observable on Basket page | D7: P3 | E7: UI | F7: Manual | G7: Spec §17 (KI-1) | H7: Documented intentional bug (KI-1) — verification only, NOT a real defect
A8: TC-007 | B8: Navigation | C8: Verify navbar displays basket item count badge | D8: P0 | E8: Functional | F8: Smoke | G8: FR-05 | H8: Basket counter not bound to state / live update broken
A9: TC-008 | B9: Navigation | C9: Verify navbar basket count badge handles large numbers (10, 99, 100+) | D9: P3 | E9: Boundary | F9: Manual | G9: FR-05 | H9: Layout regression — counter overflow / navbar wrapping
A10: TC-009 | B10: Navigation | C10: Verify navbar position behaviour on long page scroll | D10: P3 | E10: UI | F10: Manual | G10: — | H10: Sticky-header CSS regression / scroll behaviour bug
A11: TC-010 | B11: Home | C11: Verify home page hero banner renders with correct title and tagline | D11: P1 | E11: UI | F11: Regression | G11: FR-03 | H11: Hero asset missing / template content drift
A12: TC-011 | B12: Home | C12: Verify Browse Sweets CTA navigates to /sweets | D12: P2 | E12: Functional | F12: Regression | G12: FR-03 | H12: CTA link broken or wrong target URL
... A159: TC-245 | B159: Cross-cutting | C159: Verify favicon loads on all pages | D159: P3 | E159: UI | F159: Manual | G159: — | H159: Missing favicon — branding / polish gap

Sheet RTM (Reverse)
A1: TC ID | B1: Title | C1: Priority | D1: Module | E1: Requirement(s) Covered | F1: Trace Status
A2: TC-001 | B2: Verify all 5 pages load successfully via direct URL | C2: P0 | D2: Navigation | E2: FR-16, NFR-02 | F2: Traced
A3: TC-002 | B3: Verify navbar links navigate to correct pages | C3: P0 | D3: Navigation | E3: FR-16, FR-18 | F3: Traced
A4: TC-003 | B4: Verify navbar active-state highlight reflects current page | C4: P2 | D4: Navigation | E4: FR-17 | F4: Traced
A5: TC-004 | B5: Verify logo from any page returns user to home | C5: P2 | D5: Navigation | E5: FR-18 | F5: Traced
A6: TC-005 | B6: Verify footer is present on all pages with correct copyright | C6: P3 | D6: Navigation | E6: FR-16 | F6: Traced
A7: TC-006 | B7: Verify intentional broken /bout link is observable on Basket page | C7: P3 | D7: Navigation | E7: — | F7: Orphan (review)
A8: TC-007 | B8: Verify navbar displays basket item count badge | C8: P0 | D8: Navigation | E8: FR-05 | F8: Traced
A9: TC-008 | B9: Verify navbar basket count badge handles large numbers (10, 99, 100+) | C9: P3 | D9: Navigation | E9: FR-05, FR-16 | F9: Traced
A10: TC-009 | B10: Verify navbar position behaviour on long page scroll | C10: P3 | D10: Navigation | E10: FR-16 | F10: Traced
A11: TC-010 | B11: Verify home page hero banner renders with correct title and tagline | C11: P1 | D11: Home | E11: FR-03 | F11: Traced
A12: TC-011 | B12: Verify Browse Sweets CTA navigates to /sweets | C12: P2 | D12: Home | E12: FR-03 | F12: Traced
... A159: TC-245 | B159: Verify favicon loads on all pages | C159: P3 | D159: Cross-cutting | E159: FR-16 | F159: Traced

Sheet Execution Log
A1: TC ID | B1: Title | C1: Priority | D1: Module | E1: Automation | F1: Status | G1: Executed By | H1: Execution Date | I1: Defect ID | J1: Notes
A2: TC-001 | B2: Verify all 5 pages load successfully via direct URL | C2: P0 | D2: Navigation | E2: Smoke | F2: Not Run
A3: TC-002 | B3: Verify navbar links navigate to correct pages | C3: P0 | D3: Navigation | E3: Smoke | F3: Not Run
A4: TC-003 | B4: Verify navbar active-state highlight reflects current page | C4: P2 | D4: Navigation | E4: Regression | F4: Not Run
A5: TC-004 | B5: Verify logo from any page returns user to home | C5: P2 | D5: Navigation | E5: Regression | F5: Not Run
A6: TC-005 | B6: Verify footer is present on all pages with correct copyright | C6: P3 | D6: Navigation | E6: Regression | F6: Not Run
A7: TC-006 | B7: Verify intentional broken /bout link is observable on Basket page | C7: P3 | D7: Navigation | E7: Manual | F7: Not Run
A8: TC-007 | B8: Verify navbar displays basket item count badge | C8: P0 | D8: Navigation | E8: Smoke | F8: Not Run
A9: TC-008 | B9: Verify navbar basket count badge handles large numbers (10, 99, 100+) | C9: P3 | D9: Navigation | E9: Manual | F9: Not Run
A10: TC-009 | B10: Verify navbar position behaviour on long page scroll | C10: P3 | D10: Navigation | E10: Manual | F10: Not Run
A11: TC-010 | B11: Verify home page hero banner renders with correct title and tagline | C11: P1 | D11: Home | E11: Regression | F11: Not Run
A12: TC-011 | B12: Verify Browse Sweets CTA navigates to /sweets | C12: P2 | D12: Home | E12: Regression | F12: Not Run
A13: TC-012 | B13: Verify promotional banner displays 20% Off message | C13: P3 | D13: Home | E13: Regression | F13: Not Run
... A159: TC-245 | B159: Verify favicon loads on all pages | C159: P3 | D159: Cross-cutting | E159: Manual | F159: Not Run

Sheet Coverage Summary
A1: Coverage Summary Dashboard
A3: Requirements Coverage
A4: Metric | B4: Count | C4: Percentage
A5: Total Requirements (FR + NFR) | B5: 26 | C5: 100.0%
A6: Functional Requirements (FR-01..18) | B6: 18 | C6: =B6/B5 -> 0.69230769
A7: Non-Functional Requirements (NFR-01..08) | B7: 8 | C7: =B7/B5 -> 0.30769231
A8: Requirements with at least 1 test case (Covered) | B8: 26 | C8: =B8/B5 -> 1
A9: Requirements with NO test case (GAP) | B9: 0 | C9: =B9/B5 -> 0
A11: Test Case Distribution
A12: Bucket | B12: Count | C12: Percentage
A13: Total Test Cases | B13: 158 | C13: 100.0%
A14: P0 — Critical | B14: 20 | C14: =B14/B13 -> 0.12658228
A15: P1 — High | B15: 41 | C15: =B15/B13 -> 0.25949367
A16: P2 — Medium | B16: 53 | C16: =B16/B13 -> 0.33544304
A17: P3 — Low | B17: 44 | C17: =B17/B13 -> 0.27848101
A19: Smoke (PR-level CI) | B19: 8 | C19: =B19/B13 -> 0.050632911
A20: Regression (merge + nightly) | B20: 69 | C20: =B20/B13 -> 0.43670886
A21: Manual only | B21: 81 | C21: =B21/B13 -> 0.51265823
A23: Execution Status (live from Execution Log)
A24: Status | B24: Count | C24: % of Total
A25: Not Run | B25: =COUNTIF('Execution Log'!F2:F159,"Not Run") -> 158 | C25: =B25/158 -> 1
A26: Pass | B26: =COUNTIF('Execution Log'!F2:F159,"Pass") -> 0 | C26: =B26/158 -> 0
A27: Fail | B27: =COUNTIF('Execution Log'!F2:F159,"Fail") -> 0 | C27: =B27/158 -> 0
A28: Blocked | B28: =COUNTIF('Execution Log'!F2:F159,"Blocked") -> 0 | C28: =B28/158 -> 0
A29: Skipped | B29: =COUNTIF('Execution Log'!F2:F159,"Skipped") -> 0 | C29: =B29/158 -> 0

Sheet Defect Anchor
A1: Defect Anchor
A2: As defects are raised during execution, log them here AND populate the Defect ID column on the Execution Log sheet for the failed test case. The RTM (Forward) sheet will automatically aggregate defect IDs against the affected requirements.
A4: Defect ID | B4: Title | C4: Severity | D4: Priority | E4: Status | F4: Test Case ID | G4: Requirement | H4: Date Raised | I4: Owner | J4: Notes

Sheet Legend
A1: Legend & Definitions
A3: Priority
A4: Value | B4: Definition
A5: P0 | B5: Critical — must pass at exit; covers core flows and key calculations
A6: P1 | B6: High — should pass at exit; covers important features and validations
A7: P2 | B7: Medium — should be executed; covers secondary features
A8: P3 | B8: Low — nice to execute; covers edge cases and cosmetic checks
A10: Automation
A11: Value | B11: Definition
A12: Smoke | B12: Runs on every PR via CI; build rejected if any fails
A13: Regression | B13: Runs on merge to main and nightly; full automated suite
A14: Manual | B14: Manual execution only — exploratory, DevTools-driven, or visual
A16: Status (Execution Log)
A17: Value | B17: Definition
A18: Not Run | B18: Case has not yet been executed
A19: Pass | B19: All PASS conditions verified
A20: Fail | B20: A FAIL condition was observed; raise defect and record Defect ID
A21: Blocked | B21: Case cannot be executed due to environment, build, or dependency issue
A22: Skipped | B22: Case intentionally excluded for this run (with reason in Notes)
A24: Coverage Status (RTM Forward)
A25: Value | B25: Definition
A26: Covered | B26: Requirement has at least one test case mapped to it
A27: GAP | B27: Requirement has NO test case — must be addressed before execution begins
A29: Defect Severity (Defect Anchor)
A30: Value | B30: Definition
A31: Critical | B31: Core flow blocked; no workaround
A32: High | B32: Major function broken; workaround exists or feature partially works
A33: Medium | B33: Minor function broken; cosmetic with usability impact
A34: Low | B34: Cosmetic or trivial; no usability impact
A36: Defect Priority (Defect Anchor)
A37: Value | B37: Definition
A38: P1 | B38: Fix now — block exit
A39: P2 | B39: Fix this cycle — should be fixed before exit
A40: P3 | B40: Fix soon — should be fixed in the next cycle
A41: P4 | B41: Fix eventually — backlog; nice-to-have
